bm25_fusion/__init__.py
bm25_fusion/core.py
bm25_fusion/tokenization.py
bm25_fusion-0.1.4.2.dist-info/LICENSE
bm25_fusion-0.1.4.2.dist-info/METADATA
bm25_fusion-0.1.4.2.dist-info/WHEEL
bm25_fusion-0.1.4.2.dist-info/top_level.txt
bm25_fusion-0.1.4.2.dist-info/RECORD
