Metadata-Version: 2.2
Name: bm25_fusion
Version: 0.1.4.2
Summary: An ultra-fast BM25 retriever with support for multiple variants, metadata filtering, and stopword removal.
Home-page: https://github.com/Rohith-2/bm25-fusion
Author: Rohith Ramakrishnan
Author-email: Rohith Ramakrishnan <rrohith2001@gmail.com>
License: MIT License
Requires-Python: >=3.8
License-File: LICENSE
Requires-Dist: numpy
Requires-Dist: numba
Requires-Dist: nltk
Requires-Dist: h5py
Requires-Dist: tqdm
Dynamic: author
Dynamic: home-page
Dynamic: requires-python
